password_generator/__init__.py
password_generator/cli.py
passkey_generator_cli-1.0.0.dist-info/METADATA
passkey_generator_cli-1.0.0.dist-info/WHEEL
passkey_generator_cli-1.0.0.dist-info/entry_points.txt
passkey_generator_cli-1.0.0.dist-info/top_level.txt
passkey_generator_cli-1.0.0.dist-info/RECORD
