Metadata-Version: 2.4
Name: passkey-generator-cli
Version: 1.0.0
Summary: A secure and customizable password generator CLI tool
Home-page: https://github.com/MohsenBizhani/PasswordGenerator
Author: Mohsen Bizhani
Author-email: bizhani.2002@gmail.com
Classifier: Programming Language :: Python :: 3
Classifier: Programming Language :: Python :: 3.6
Classifier: Programming Language :: Python :: 3.7
Classifier: Programming Language :: Python :: 3.8
Classifier: Programming Language :: Python :: 3.9
Classifier: License :: OSI Approved :: MIT License
Classifier: Operating System :: OS Independent
Classifier: Environment :: Console
Classifier: Intended Audience :: Developers
Classifier: Intended Audience :: End Users/Desktop
Classifier: Topic :: Security
Classifier: Topic :: Utilities
Requires-Python: >=3.6
Requires-Dist: pyperclip>=1.8.2
Dynamic: author
Dynamic: author-email
Dynamic: classifier
Dynamic: description
Dynamic: description-content-type
Dynamic: home-page
Dynamic: requires-dist
Dynamic: requires-python
Dynamic: summary
